cam_viewer/__init__.py
cam_viewer/functions.py
cam_viewer-0.0.3.dist-info/LICENSE
cam_viewer-0.0.3.dist-info/METADATA
cam_viewer-0.0.3.dist-info/WHEEL
cam_viewer-0.0.3.dist-info/top_level.txt
cam_viewer-0.0.3.dist-info/RECORD
