Metadata-Version: 2.1
Name: cam_viewer
Version: 0.0.3
Summary: Python library for connecting to m3u8 cameras
Author-email: "Amadeus (Wasys)" <tubik.corp@gmail.com>
Project-URL: Homepage, https://github.com/Vasysik/cam-viewer
Project-URL: Issues, https://github.com/Vasysik/cam-viewer/issues
Classifier: Programming Language :: Python :: 3
Classifier: License :: OSI Approved :: MIT License
Classifier: Operating System :: OS Independent
Requires-Python: >=3.8
License-File: LICENSE
